respysive/__init__.py
respysive/container.py
respysive/content.py
respysive/presentation.py
respysive/utils.py
respysive/version.py
respysive/.ipynb_checkpoints/presentation-checkpoint.py
respysive_slide-1.1.15.dist-info/licenses/LICENSE
respysive_slide-1.1.15.dist-info/WHEEL
respysive_slide-1.1.15.dist-info/METADATA
respysive_slide-1.1.15.dist-info/RECORD
