Metadata-Version: 2.4
Name: respysive-slide
Version: 1.1.15
Summary: A Python package that allows you to create interactive presentations using Python, Bootstrap and Reveal.js. Charts from Altair and Plotly can also be added
Keywords: slide,presentation,reveal.js,Bootstrap
Author: fbxyz
Requires-Python: >=3.7
Classifier: License :: OSI Approved :: MIT License
License-File: LICENSE
Requires-Dist: beautifulsoup4
Requires-Dist: requests
Requires-Dist: matplotlib
Requires-Dist: ipython ; extra == "dev"
Requires-Dist: markdown ; extra == "dev"
Project-URL: Home, https://github.com/fbxyz/respysive-slide
Provides-Extra: dev
